README.md
setup.cfg
setup.py
edwar/__init__.py
edwar/configure.py
edwar/errors.py
edwar/install.py
edwar/runner.py
edwar.egg-info/PKG-INFO
edwar.egg-info/SOURCES.txt
edwar.egg-info/dependency_links.txt
edwar.egg-info/requires.txt
edwar.egg-info/top_level.txt
edwar/loaders/__init__.py
edwar/loaders/bioplux.py
edwar/loaders/e4.py
edwar/loaders/everion.py
edwar/loaders/loader.py
edwar/loaders/onyx.py
edwar/loaders/utils.py
edwar/parsers/__init__.py
edwar/parsers/parameters.py
edwar/parsers/parsers.py
edwar/parsers/utils.py
edwar/parsers/acc/__init__.py
edwar/parsers/eda/__init__.py
edwar/parsers/eda/adaptive_filtering.py
edwar/parsers/eda/art_detect.py
edwar/parsers/eda/cvxEDA.py
edwar/parsers/eda/eda.py
edwar/parsers/eda/eda_wavelet_thresholding.py
edwar/parsers/eda/nlms.py
edwar/parsers/eda_explorer/AccelerometerFeatureExtractionScript.py
edwar/parsers/eda_explorer/ArtifactClassifiers.py
edwar/parsers/eda_explorer/EDA-Peak-Detection-Script.py
edwar/parsers/eda_explorer/EDA_Artifact_Detection_Script.py
edwar/parsers/eda_explorer/__init__.py
edwar/parsers/eda_explorer/classify.py
edwar/parsers/eda_explorer/load_files.py
edwar/parsers/ibi/__init__.py
edwar/parsers/ibi/parser.py
edwar/parsers/ibi/variables.py
edwar/parsers/temp/__init__.py
edwar/savers/__init__.py
edwar/savers/save_csv.py
edwar/savers/save_db.py
edwar/utils/__init__.py
edwar/utils/configuration.py
edwar/utils/db_connection.py
edwar/utils/logs.py
edwar/utils/rw_ini.py
edwar/utils/user_input.py