Metadata-Version: 2.1
Name: edwar
Version: 0.9.1.1
Summary: signal Error Detection for WBSN And data1 Recovery
Home-page: https://github.com/greenlsi/edwar
Author: Miguel Merino
Author-email: miguel_dreimal_30@hotmail.com
License: MIT
Download-URL: https://github.com/greenlsi/edwar/archive/v_092.tar.gz
Keywords: EDA,RECOVERY,SIGNAL
Platform: UNKNOWN
Classifier: Development Status :: 3 - Alpha
Classifier: Intended Audience :: Developers
Classifier: Topic :: Software Development :: Build Tools
Classifier: License :: OSI Approved :: MIT License
Classifier: Programming Language :: Python :: 3
Classifier: Programming Language :: Python :: 3.4
Classifier: Programming Language :: Python :: 3.5
Classifier: Programming Language :: Python :: 3.6
Classifier: Programming Language :: Python :: 3.7
